chinacapi/__init__.py
chinacapi/chinac_api.py
chinacapi/cloud_phone_api.py
chinacapi/cloud_phone_region.py
chinacapi/utils.py
chinacapi/exception/__init__.py
chinacapi/exception/cloud_phone_status.py
chinacapi-0.1.3.dist-info/LICENSE
chinacapi-0.1.3.dist-info/METADATA
chinacapi-0.1.3.dist-info/WHEEL
chinacapi-0.1.3.dist-info/top_level.txt
chinacapi-0.1.3.dist-info/RECORD
