Metadata-Version: 2.1
Name: chinacapi
Version: 0.1.3
Summary: A chinac api operator
Home-page: https://github.com/AkagiYui/ChinacApi
Author: AkagiYui
Author-email: akagiyui@yeah.net
Classifier: Development Status :: 4 - Beta
Classifier: Programming Language :: Python :: 3.7
Classifier: Intended Audience :: Developers
Classifier: License :: OSI Approved :: MIT License
Classifier: Operating System :: OS Independent
Requires-Python: >=3.7
License-File: LICENSE
